src/__init__.py
src/file.py
img2social-0.1.5.dist-info/METADATA
img2social-0.1.5.dist-info/WHEEL
img2social-0.1.5.dist-info/entry_points.txt
img2social-0.1.5.dist-info/top_level.txt
img2social-0.1.5.dist-info/RECORD
