Metadata-Version: 2.1
Name: img2social
Version: 0.1.5
Summary: Create engaging images for socials quicker.
Home-page: https://github.com/dodothedeveloper/img2social
Author: dodo
Author-email: dodothedeveloper@gmail.com
Classifier: Programming Language :: Python :: 3
Classifier: License :: OSI Approved :: MIT License
Classifier: Operating System :: OS Independent
Requires-Python: >=3.10
